{
  "type": "FeatureCollection",
  "features": [
    {
      "type": "Feature",
      "properties": {
        "marker-color": "#ff8000",
        "marker-size": "medium",
        "marker-symbol": "parking",
        "name": "Font Romeu",
        "region": [
          "Francia",
          "Pirineo Oriental",
          "Font Romeu"
        ],
        "tags": {
          "gratis": true,
          "agua": false,
          "wc": false,
          "luz": false,
          "invierno": true,
          "urbano": true
        },
        "indication": "A la salida de Font Romeu en dirección a la estación de esquí a la derecha, hay un parking para autocaravanas, tranquilo e iluminado",
        "other": "Estación de esquí a 5 minutos, varias más en todo el valle. Cerca de Andorra.\nCon el forfait de Font Romeu se puede coger una visita a los Baños de Saint Thomas (+20min) con piscinas exteriores calientes (muy recomendable)",
        "googlemaps": {
          "coordinates": [
            "42°30'20.1\"N",
            "2°02'43.8\"E"
          ],
          "photos": [
            "https://www.google.fr/maps/place/42%C2%B030'20.1%22N+2%C2%B002'43.8%22E/@42.505583,2.0449164,157m/data=!3m2!1e3!4b1!4m5!3m4!1s0x0:0x0!8m2!3d42.505582!4d2.045493"
          ]
        }
      },
      "geometry": {
        "type": "Point",
        "coordinates": [
          2.0453426241874695,
          42.505493517282225
        ]
      }
    }
  ]
}
